{
	"#comment": "Level Of The Day Default",
	"objects": [
		{
			"objclass": "LevelDefinition",
			"objdata": {
				"DraperPromo": "none",
				"LevelNumber": 5,
				"LevelPowerupSet": "LevelPowerupsDisabled",
				"Loot": "RTID(DefaultLoot@LevelModules)",
				"Modules": [
					"RTID(StandardIntro@LevelModules)",
					"RTID(LevelEscalationModule@CurrentLevel)",
					"RTID(DefaultSunDropper@LevelModules)",
					"RTID(FrontLawnMowers@LevelModules)",
					"RTID(NewWaves@CurrentLevel)",
					"RTID(DefaultZombieWinCondition@LevelModules)",
					"RTID(SeedBank@CurrentLevel)",
					"RTID(ZombiesDeadWinCon@LevelModules)",
					"RTID(SliderPlacement@CurrentLevel)",
					"RTID(FrozenPlantPlacement@CurrentLevel)"
				],
				"Name": "[LTE_LEVEL_NAME_SPORTZBALL]",
				"StageModule": "RTID(SportzballStage@LevelModules)",
				"StartingSun": 475
			}
		},
		{
			"aliases": [
				"SeedBank"
			],
			"objclass": "SeedBankProperties",
			"objdata": {
				"PlantExcludeList": [
					"spearmint",
					"peppermint",
					"appeasemint",
					"concealmint",
					"filamint",
					"wintermint",
					"bombardmint",
					"armamint",
					"ailmint",
					"reinforcemint",
					"containmint",
					"enchantmint",
					"enchantmint",
					"enforcemint",
					"enlightenmint",
					"blover"
				],
				"PresetPlantList": [],
				"SelectionMethod": "chooser"
			}
		},
		{
			"aliases": [
				"FrozenPlantPlacement"
			],
			"objclass": "InitialPlantProperties",
			"objdata": {
				"InitialPlantPlacements": [
					{
						"GridX": 4,
						"GridY": 0,
						"Level": "-1",
						"TypeName": "tallnut"
					},
					{
						"GridX": 4,
						"GridY": 1,
						"Level": "-1",
						"TypeName": "tallnut"
					},
					{
						"GridX": 6,
						"GridY": 2,
						"Level": "-1",
						"TypeName": "explodeonut"
					},
					{
						"GridX": 2,
						"GridY": 2,
						"Level": "-1",
						"TypeName": "explodeonut"
					},
					{
						"GridX": 5,
						"GridY": 3,
						"Level": "-1",
						"TypeName": "tallnut"
					},
					{
						"GridX": 5,
						"GridY": 4,
						"Level": "-1",
						"TypeName": "tallnut"
					}
				]
			}
		},
		{
			"aliases": [
				"SliderPlacement"
			],
			"objclass": "InitialGridItemProperties",
			"objdata": {
				"InitialGridItemPlacements": [
					{
						"GridX": 7,
						"GridY": 0,
						"TypeName": "slider_down_modern"
					},
					{
						"GridX": 3,
						"GridY": 0,
						"TypeName": "slider_down_modern"
					},
					{
						"GridX": 7,
						"GridY": 1,
						"TypeName": "slider_down_modern"
					},
					{
						"GridX": 3,
						"GridY": 1,
						"TypeName": "slider_down_modern"
					},
					{
						"GridX": 5,
						"GridY": 1,
						"TypeName": "slider_up_modern"
					},
					{
						"GridX": 5,
						"GridY": 2,
						"TypeName": "slider_up_modern"
					},
					{
						"GridX": 2,
						"GridY": 3,
						"TypeName": "slider_up_modern"
					},
					{
						"GridX": 6,
						"GridY": 3,
						"TypeName": "slider_up_modern"
					},
					{
						"GridX": 2,
						"GridY": 4,
						"TypeName": "slider_up_modern"
					},
					{
						"GridX": 6,
						"GridY": 4,
						"TypeName": "slider_up_modern"
					}
				]
			}
		},
		{
			"aliases": [
				"LevelEscalationModule"
			],
			"objclass": "LevelEscalationModuleProperties",
			"objdata": {
				"FlagCount": 1,
				"PlantfoodToSpawnCount": 0,
				"PointIncrementPerWave": 0,
				"StartingPoints": 0,
				"WaveManagerProps": "RTID(WaveManagerProps@CurrentLevel)",
				"WavesPerFlag": 9,
				"ZombiePool": [
					"RTID(summer_basic@ZombieTypes)"
				]
			}
		},
		{
			"aliases": [
				"WaveManagerProps"
			],
			"objclass": "WaveManagerProperties",
			"objdata": {
				"MaxNextWaveHealthPercentage": 0.6,
				"MinNextWaveHealthPercentage": 0.4,
				"Waves": [
					[
						"RTID(Wave1@CurrentLevel)"
					],
					[
						"RTID(Wave2@CurrentLevel)"
					],
					[
						"RTID(Wave3@CurrentLevel)"
					],
					[
						"RTID(Wave4@CurrentLevel)"
					],
					[
						"RTID(Wave5@CurrentLevel)"
					],
					[
						"RTID(Wave6@CurrentLevel)"
					],
					[
						"RTID(Wave7@CurrentLevel)"
					],
					[
						"RTID(Wave8@CurrentLevel)"
					],
					[
						"RTID(Wave9@CurrentLevel)"
					]
				]
			}
		},
		{
			"aliases": [
				"Wave1"
			],
			"objclass": "SpawnZombiesJitteredWaveActionProps",
			"objdata": {
				"Zombies": [
					{
						"Row": "1",
						"Type": "RTID(summer_basic@ZombieTypes)"
					},
					{
						"Row": "2",
						"Type": "RTID(summer_basic@ZombieTypes)"
					},
					{
						"Row": "3",
						"Type": "RTID(summer_basic@ZombieTypes)"
					},
					{
						"Row": "4",
						"Type": "RTID(summer_basic@ZombieTypes)"
					}
				]
			}
		},
		{
			"aliases": [
				"Wave2"
			],
			"objclass": "SpawnZombiesJitteredWaveActionProps",
			"objdata": {
				"AdditionalPlantfood": 1,
				"Zombies": [
					{
						"Row": "1",
						"Type": "RTID(sportzball_buckethead@ZombieTypes)"
					},
					{
						"Row": "2",
						"Type": "RTID(summer_basic@ZombieTypes)"
					},
					{
						"Row": "3",
						"Type": "RTID(summer_basic@ZombieTypes)"
					},
					{
						"Row": "4",
						"Type": "RTID(sportzball_buckethead@ZombieTypes)"
					}
				]
			}
		},
		{
			"aliases": [
				"Wave3"
			],
			"objclass": "SpawnZombiesJitteredWaveActionProps",
			"objdata": {
				"AdditionalPlantfood": 1,
				"Zombies": [
					{
						"Row": "1",
						"Type": "RTID(summer_armor2@ZombieTypes)"
					},
					{
						"Row": "2",
						"Type": "RTID(sportzball_buckethead@ZombieTypes)"
					},
					{
						"Row": "3",
						"Type": "RTID(sportzball_buckethead@ZombieTypes)"
					},
					{
						"Row": "4",
						"Type": "RTID(summer_armor2@ZombieTypes)"
					}
				]
			}
		},
		{
			"aliases": [
				"Wave4"
			],
			"objclass": "SpawnZombiesJitteredWaveActionProps",
			"objdata": {
				"AdditionalPlantfood": 1,
				"Zombies": [
					{
						"Row": "1",
						"Type": "RTID(future_armor4@ZombieTypes)"
					},
					{
						"Row": "2",
						"Type": "RTID(summer_armor2@ZombieTypes)"
					},
					{
						"Row": "3",
						"Type": "RTID(summer_armor2@ZombieTypes)"
					},
					{
						"Row": "4",
						"Type": "RTID(future_armor4@ZombieTypes)"
					}
				]
			}
		},
		{
			"aliases": [
				"Wave5"
			],
			"objclass": "SpawnZombiesJitteredWaveActionProps",
			"objdata": {
				"AdditionalPlantfood": 1,
				"Zombies": [
					{
						"Row": "1",
						"Type": "RTID(sportzball_balloon@ZombieTypes)"
					},
					{
						"Row": "2",
						"Type": "RTID(sportzball_balloon@ZombieTypes)"
					},
					{
						"Row": "3",
						"Type": "RTID(sportzball_balloon@ZombieTypes)"
					},
					{
						"Row": "4",
						"Type": "RTID(sportzball_balloon@ZombieTypes)"
					}
				]
			}
		},
		{
			"aliases": [
				"Wave6"
			],
			"objclass": "SpawnZombiesJitteredWaveActionProps",
			"objdata": {
				"AdditionalPlantfood": 1,
				"Zombies": [
					{
						"Row": "1",
						"Type": "RTID(modern_superfanimp@ZombieTypes)"
					},
					{
						"Row": "2",
						"Type": "RTID(modern_superfanimp@ZombieTypes)"
					},
					{
						"Row": "3",
						"Type": "RTID(modern_superfanimp@ZombieTypes)"
					},
					{
						"Row": "4",
						"Type": "RTID(modern_superfanimp@ZombieTypes)"
					}
				]
			}
		},
		{
			"aliases": [
				"Wave7"
			],
			"objclass": "SpawnZombiesJitteredWaveActionProps",
			"objdata": {
				"AdditionalPlantfood": 1,
				"Zombies": [
					{
						"Row": "1",
						"Type": "RTID(sportzball_wizard@ZombieTypes)"
					},
					{
						"Row": "2",
						"Type": "RTID(sportzball_buckethead@ZombieTypes)"
					},
					{
						"Row": "3",
						"Type": "RTID(sportzball_buckethead@ZombieTypes)"
					},
					{
						"Row": "4",
						"Type": "RTID(sportzball_wizard@ZombieTypes)"
					}
				]
			}
		},
		{
			"aliases": [
				"Wave8"
			],
			"objclass": "SpawnZombiesJitteredWaveActionProps",
			"objdata": {
				"AdditionalPlantfood": 1,
				"Zombies": [
					{
						"Row": "1",
						"Type": "RTID(summer_imp@ZombieTypes)"
					},
					{
						"Row": "2",
						"Type": "RTID(summer_imp@ZombieTypes)"
					},
					{
						"Row": "3",
						"Type": "RTID(summer_imp@ZombieTypes)"
					},
					{
						"Row": "4",
						"Type": "RTID(summer_imp@ZombieTypes)"
					}
				]
			}
		},
		{
			"aliases": [
				"Wave9"
			],
			"objclass": "SpawnZombiesJitteredWaveActionProps",
			"objdata": {
				"AdditionalPlantfood": 1,
				"Zombies": [
					{
						"Row": "1",
						"Type": "RTID(modern_superfanimp@ZombieTypes)"
					},
					{
						"Row": "2",
						"Type": "RTID(modern_allstar@ZombieTypes)"
					},
					{
						"Row": "3",
						"Type": "RTID(summer_gargantuar@ZombieTypes)"
					},
					{
						"Row": "4",
						"Type": "RTID(modern_superfanimp@ZombieTypes)"
					}
				]
			}
		},
		{
			"aliases": [
				"NewWaves"
			],
			"objclass": "WaveManagerModuleProperties",
			"objdata": {}
		}
	],
	"version": 1
}