{
	"objects": [
		{
			"objclass": "LevelDefinition",
			"objdata": {
				"LevelNumber": 5,
				"LevelPowerupSet": "LevelPowerupsDisabled",
				"Loot": "RTID(DefaultLoot@LevelModules)",
				"Modules": [
					"RTID(StandardIntro@LevelModules)",
					"RTID(LevelEscalationModule@CurrentLevel)",
					"RTID(WestMowers@LevelModules)",
					"RTID(NewWaves@CurrentLevel)",
					"RTID(DefaultZombieWinCondition@LevelModules)",
					"RTID(CowboyRails@CurrentLevel)",
					"RTID(ConveyorBelt@CurrentLevel)",
					"RTID(ZombiesDeadWinCon@LevelModules)"
				],
				"Name": "[LTE_POTW_LEVEL_NAME]",
				"AssociatedPlant": "bombegranate",
				"NormalPresentTable": "egypt_normal_01",
				"ShinyPresentTable": "egypt_shiny_01",
				"StageModule": "RTID(WestStage@LevelModules)"
			}
		},
		{
			"aliases": [
				"CowboyRails"
			],
			"objclass": "RailcartProperties",
			"objdata": {
				"RailcartType": "railcart_cowboy",
				"Railcarts": [
					{
						"Column": 0,
						"Row": 2
					}
				],
				"Rails": [
					{
						"Column": 0,
						"RowEnd": 4,
						"RowStart": 0
					}
				]
			}
		},
		{
			"aliases": [
				"LevelEscalationModule"
			],
			"objclass": "LevelEscalationModuleProperties",
			"objdata": {
				"FlagCount": 3,
				"MaxPoints": 9000,
				"PlantfoodToSpawnCount": 2,
				"PointIncrementPerWave": 150,
				"StartingPoints": 100,
				"WaveManagerProps": "RTID(WaveManagerProps@CurrentLevel)",
				"WavesPerFlag": 4,
				"ZombiePool": [
					"RTID(mummy_armor2@ZombieTypes)",
					"RTID(mummy@ZombieTypes)",
					"RTID(mummy_armor1@ZombieTypes)"
				]
			}
		},
		{
			"aliases": [
				"WaveManagerProps"
			],
			"objclass": "WaveManagerProperties",
			"objdata": {
				"MaxNextWaveHealthPercentage": 0.9,
				"MinNextWaveHealthPercentage": 0.8,
				"Waves": [
					[
						"RTID(Wave1@CurrentLevel)"
					],
					[
						"RTID(Wave2@CurrentLevel)"
					],
					[
						"RTID(Wave3@CurrentLevel)"
					],
					[
						"RTID(Wave4@CurrentLevel)",
						"RTID(Wave4ModConveyor0@CurrentLevel)"
					],
					[
						"RTID(Wave5@CurrentLevel)"
					],
					[
						"RTID(Wave6@CurrentLevel)"
					],
					[
						"RTID(Wave7@CurrentLevel)"
					],
					[
						"RTID(Wave8@CurrentLevel)"
					],
					[
						"RTID(Wave9@CurrentLevel)"
					],
					[
						"RTID(Wave10@CurrentLevel)"
					],
					[
						"RTID(Wave11@CurrentLevel)"
					],
					[
						"RTID(Wave12@CurrentLevel)"
					]
				],
				"ZombieCountdownFirstWaveConveyorSecs": 5,
				"ZombieCountdownFirstWaveSecs": 12,
				"ZombieCountdownHugeWaveDelay": 5
			}
		},
		{
			"aliases": [
				"Wave1"
			],
			"objclass": "SpawnZombiesJitteredWaveActionProps",
			"objdata": {
				"ForcedCondition": {},
				"Zombies": [
					{
						"Row": "3",
						"Type": "RTID(mummy@ZombieTypes)"
					},
					{
						"Row": "2",
						"Type": "RTID(mummy@ZombieTypes)"
					},
					{
						"Row": "4",
						"Type": "RTID(mummy@ZombieTypes)"
					}
				]
			}
		},
		{
			"aliases": [
				"Wave2"
			],
			"objclass": "SpawnZombiesJitteredWaveActionProps",
			"objdata": {
				"ForcedCondition": {},
				"Zombies": [
					{
						"Row": "4",
						"Type": "RTID(mummy_armor1@ZombieTypes)"
					},
					{
						"Row": "5",
						"Type": "RTID(mummy_armor1@ZombieTypes)"
					},
					{
						"Row": "3",
						"Type": "RTID(mummy_armor1@ZombieTypes)"
					}
				]
			}
		},
		{
			"aliases": [
				"Wave3"
			],
			"objclass": "SpawnZombiesJitteredWaveActionProps",
			"objdata": {
				"ForcedCondition": {},
				"Zombies": [
					{
						"Row": "5",
						"Type": "RTID(mummy_armor1@ZombieTypes)"
					},
					{
						"Row": "4",
						"Type": "RTID(mummy_armor1@ZombieTypes)"
					},
					{
						"Row": "3",
						"Type": "RTID(lostcity_excavator@ZombieTypes)"
					}
				]
			}
		},
		{
			"aliases": [
				"Wave4"
			],
			"objclass": "SpawnZombiesJitteredWaveActionProps",
			"objdata": {
				"ForcedCondition": {},
				"Zombies": [
					{
						"Row": "5",
						"Type": "RTID(mummy_armor1@ZombieTypes)"
					},
					{
						"Row": "4",
						"Type": "RTID(mummy_armor1@ZombieTypes)"
					},
					{
						"Row": "3",
						"Type": "RTID(lostcity_excavator@ZombieTypes)"
					}
				]
			}
		},
		{
			"aliases": [
				"Wave5"
			],
			"objclass": "SpawnZombiesJitteredWaveActionProps",
			"objdata": {
				"AdditionalPlantfood": 1,
				"ForcedCondition": {},
				"Zombies": [
					{
						"Row": "2",
						"Type": "RTID(dark_juggler@ZombieTypes)"
					},
					{
						"Row": "2",
						"Type": "RTID(dark_juggler@ZombieTypes)"
					},
					{
						"Row": "3",
						"Type": "RTID(dark_juggler@ZombieTypes)"
					},
					{
						"Row": "3",
						"Type": "RTID(camel_manyhump@ZombieTypes)"
					},
					{
						"Row": "4",
						"Type": "RTID(dark_juggler@ZombieTypes)"
					},
					{
						"Row": "4",
						"Type": "RTID(camel_manyhump@ZombieTypes)"
					},
					{
						"Row": "5",
						"Type": "RTID(dark_juggler@ZombieTypes)"
					},
					{
						"Row": "5",
						"Type": "RTID(camel_manyhump@ZombieTypes)"
					}
				]
			}
		},
		{
			"aliases": [
				"Wave6"
			],
			"objclass": "SpawnZombiesJitteredWaveActionProps",
			"objdata": {
				"ForcedCondition": {},
				"Zombies": [
					{
						"Type": "RTID(camel_manyhump@ZombieTypes)"
					},
					{
						"Row": "2",
						"Type": "RTID(camel_manyhump@ZombieTypes)"
					}
				]
			}
		},
		{
			"aliases": [
				"Wave7"
			],
			"objclass": "SpawnZombiesJitteredWaveActionProps",
			"objdata": {
				"ForcedCondition": {},
				"Zombies": [
					{
						"Type": "RTID(pharaoh@ZombieTypes)"
					},
					{
						"Row": "2",
						"Type": "RTID(pharaoh@ZombieTypes)"
					}
				]
			}
		},
		{
			"aliases": [
				"Wave8"
			],
			"objclass": "SpawnZombiesJitteredWaveActionProps",
			"objdata": {
				"ForcedCondition": {},
				"Zombies": [
					{
						"Type": "RTID(lostcity_excavator@ZombieTypes)"
					},
					{
						"Type": "RTID(lostcity_excavator@ZombieTypes)"
					}
				]
			}
		},
		{
			"aliases": [
				"Wave9"
			],
			"objclass": "SpawnZombiesJitteredWaveActionProps",
			"objdata": {
				"ForcedCondition": {},
				"Zombies": [
					{
						"Type": "RTID(lostcity_excavator@ZombieTypes)"
					},
					{
						"Row": "5",
						"Type": "RTID(football_mech@ZombieTypes)"
					},
					{
						"Row": "4",
						"Type": "RTID(pharaoh@ZombieTypes)"
					},
					{
						"Row": "3",
						"Type": "RTID(football_mech@ZombieTypes)"
					},
					{
						"Row": "2",
						"Type": "RTID(lostcity_excavator@ZombieTypes)"
					}
				]
			}
		},
		{
			"aliases": [
				"NewWaves"
			],
			"objclass": "WaveManagerModuleProperties",
			"objdata": {}
		},
		{
			"aliases": [
				"ConveyorBelt"
			],
			"objclass": "ConveyorSeedBankProperties",
			"objdata": {
				"DropDelayConditions": [
					{
						"Delay": 3
					},
					{
						"Delay": 6,
						"MaxPackets": 2
					},
					{
						"Delay": 9,
						"MaxPackets": 4
					},
					{
						"Delay": 12,
						"MaxPackets": 8
					}
				],
				"InitialPlantList": [
					{
						"Level": -1,
						"MaxDelivered": -1,
						"MaxWeightFactor": 0.1,
						"MinWeightFactor": 10,
						"PlantType": "bombegranate",
						"Weight": 50
					},
					{
						"Level": -1,
						"MaxDelivered": -1,
						"MaxWeightFactor": 0.1,
						"MinWeightFactor": 10,
						"MaxCount": 3,
						"PlantType": "coconutcannon",
						"Weight": 25
					}
				],
				"SpeedConditions": [
					{
						"Speed": 100
					}
				]
			}
		},
		{
			"aliases": [
				"Wave10"
			],
			"objclass": "SpawnZombiesJitteredWaveActionProps",
			"objdata": {
				"ForcedCondition": {},
				"Zombies": [
					{
						"Row": "5",
						"Type": "RTID(lostcity_excavator@ZombieTypes)"
					},
					{
						"Row": "3",
						"Type": "RTID(lostcity_excavator@ZombieTypes)"
					}
				]
			}
		},
		{
			"aliases": [
				"Wave11"
			],
			"objclass": "SpawnZombiesJitteredWaveActionProps",
			"objdata": {
				"ForcedCondition": {},
				"Zombies": [
					{
						"Row": "5",
						"Type": "RTID(lostcity_excavator@ZombieTypes)"
					},
					{
						"Row": "3",
						"Type": "RTID(lostcity_excavator@ZombieTypes)"
					}
				]
			}
		},
		{
			"aliases": [
				"Wave4ModConveyor0"
			],
			"objclass": "ModifyConveyorWaveActionProps",
			"objdata": {
				"Add": [
					{
						"MaxCount": 1,
						"MaxWeightFactor": 0.5,
						"MinWeightFactor": 0.1,
						"Type": "RTID(stallia@PlantTypes)",
						"Weight": 20
					}
				]
			}
		},
		{
			"aliases": [
				"Wave12"
			],
			"objclass": "SpawnZombiesJitteredWaveActionProps",
			"objdata": {
				"ForcedCondition": {},
				"Zombies": [
					{
						"Row": "4",
						"Type": "RTID(lostcity_excavator@ZombieTypes)"
					},
					{
						"Row": "4",
						"Type": "RTID(lostcity_excavator@ZombieTypes)"
					},
					{
						"Type": "RTID(lostcity_excavator@ZombieTypes)"
					},
					{
						"Type": "RTID(pharaoh@ZombieTypes)"
					},
					{
						"Row": "5",
						"Type": "RTID(pharaoh@ZombieTypes)"
					},
					{
						"Row": "3",
						"Type": "RTID(pharaoh@ZombieTypes)"
					},
					{
						"Row": "2",
						"Type": "RTID(lostcity_excavator@ZombieTypes)"
					},
					{
						"Row": "2",
						"Type": "RTID(pharaoh@ZombieTypes)"
					}
				]
			}
		}
	],
	"version": 1
}