{
	"#comment": "Level Of The Day Default",
	"objects": [
		{
			"objclass": "LevelDefinition",
			"objdata": {
				"DraperPromo": "",
				"FirstIntroNarrative": "",
				"FirstOutroNarrative": "BWB_LTE_2023_6",
				"LevelNumber": 15,
				"LevelPowerupSet": "LevelPowerupsDisabled",
				"Loot": "RTID(DefaultLoot@LevelModules)",
				"Modules": [
					"RTID(StandardIntro@LevelModules)",
					"RTID(LevelEscalationModule@CurrentLevel)",
					"RTID(DefaultSunDropper@LevelModules)",
					"RTID(BeachMowers@LevelModules)",
					"RTID(NewWaves@CurrentLevel)",
					"RTID(DefaultZombieWinCondition@LevelModules)",
					"RTID(Gravestones@CurrentLevel)",
					"RTID(SeedBank@CurrentLevel)",
					"RTID(ZombiesDeadWinCon@LevelModules)",
					"RTID(LilypadPlacement@CurrentLevel)",
					"RTID(Tide@CurrentLevel)"
				],
				"Name": "[LTE_LEVEL_NAME_BEACH]",
				"StageModule": "RTID(BeachStage@LevelModules)",
				"StartingSun": 1000
			}
		},
		{
			"aliases": [
				"SeedBank"
			],
			"objclass": "SeedBankProperties",
			"objdata": {
				"PresetPlantList": [
					{
						"Level": -1,
						"PlantType": "lilypad"
					},
					{
						"Level": -1,
						"PlantType": "tanglekelp"
					},
					{
						"Level": -1,
						"PlantType": "guacodile"
					},
					{
						"Level": -1,
						"PlantType": "banana"
					}
				],
				"SelectionMethod": "chooser"
			}
		},
		{
			"aliases": [
				"Tide"
			],
			"objclass": "TideProperties",
			"objdata": {
				"StartingWaveLocation": 9
			}
		},
		{
			"aliases": [
				"LilypadPlacement"
			],
			"objclass": "InitialPlantProperties",
			"objdata": {
				"InitialPlantPlacements": [
					{
						"GridX": 6,
						"GridY": 0,
						"TypeName": "lilypad"
					},
					{
						"GridX": 0,
						"GridY": 1,
						"TypeName": "lilypad"
					},
					{
						"GridX": 2,
						"GridY": 1,
						"TypeName": "lilypad"
					},
					{
						"GridX": 5,
						"GridY": 1,
						"TypeName": "lilypad"
					},
					{
						"GridX": 0,
						"GridY": 2,
						"TypeName": "lilypad"
					},
					{
						"GridX": 5,
						"GridY": 3,
						"TypeName": "lilypad"
					},
					{
						"GridX": 1,
						"GridY": 3,
						"TypeName": "lilypad"
					},
					{
						"GridX": 7,
						"GridY": 4,
						"TypeName": "lilypad"
					}
				]
			}
		},
		{
			"aliases": [
				"LevelEscalationModule"
			],
			"objclass": "LevelEscalationModuleProperties",
			"objdata": {
				"FlagCount": 3,
				"PlantfoodToSpawnCount": 6,
				"PointIncrementPerWave": 75,
				"StartingPoints": -500,
				"WaveManagerProps": "RTID(WaveManagerProps@CurrentLevel)",
				"WavesPerFlag": 7,
				"ZombiePool": [
					"RTID(beach_fastswimmer@ZombieTypes)",
					"RTID(beach_snorkel@ZombieTypes)",
					"RTID(beach_surfer@ZombieTypes)",
					"RTID(beach_octopus@ZombieTypes)"
				]
			}
		},
		{
			"aliases": [
				"WaveManagerProps"
			],
			"objclass": "WaveManagerProperties",
			"objdata": {
				"MaxNextWaveHealthPercentage": 0.9,
				"MinNextWaveHealthPercentage": 0.7,
				"Waves": [
					[
						"RTID(Wave1@CurrentLevel)"
					],
					[
						"RTID(Wave2@CurrentLevel)",
						"RTID(Wave2TidalChangeEvent0@CurrentLevel)"
					],
					[
						"RTID(Wave3@CurrentLevel)"
					],
					[
						"RTID(Wave4@CurrentLevel)"
					],
					[
						"RTID(Wave5@CurrentLevel)"
					],
					[
						"RTID(Wave6@CurrentLevel)",
						"RTID(Wave6TidalChangeEvent0@CurrentLevel)"
					],
					[
						"RTID(Wave7@CurrentLevel)",
						"RTID(Wave7LowTideEvent0@CurrentLevel)",
						"RTID(Wave7TidalChangeEvent0@CurrentLevel)"
					],
					[
						"RTID(Wave8@CurrentLevel)"
					],
					[
						"RTID(Wave9@CurrentLevel)"
					],
					[
						"RTID(Wave10@CurrentLevel)"
					],
					[
						"RTID(Wave11@CurrentLevel)",
						"RTID(Wave11TidalChangeEvent0@CurrentLevel)"
					],
					[
						"RTID(Wave12@CurrentLevel)",
						"RTID(Wave12LowTideEvent0@CurrentLevel)"
					],
					[
						"RTID(Wave13@CurrentLevel)"
					],
					[
						"RTID(Wave14@CurrentLevel)",
						"RTID(Wave14TidalChangeEvent0@CurrentLevel)"
					],
					[
						"RTID(Wave15@CurrentLevel)"
					],
					[
						"RTID(Wave16@CurrentLevel)",
						"RTID(Wave16TidalChangeEvent0@CurrentLevel)"
					],
					[
						"RTID(Wave17@CurrentLevel)"
					],
					[
						"RTID(Wave18@CurrentLevel)",
						"RTID(Wave18LowTideEvent0@CurrentLevel)"
					],
					[
						"RTID(Wave19@CurrentLevel)",
						"RTID(Wave19TidalChangeEvent0@CurrentLevel)"
					],
					[
						"RTID(Wave20@CurrentLevel)",
						"RTID(Wave20TidalChangeEvent0@CurrentLevel)"
					],
					[
						"RTID(Wave21@CurrentLevel)",
						"RTID(Wave21LowTideEvent0@CurrentLevel)"
					]
				],
				"ZombieCountdownFirstWaveSecs": 6
			}
		},
		{
			"aliases": [
				"Wave1"
			],
			"objclass": "SpawnZombiesJitteredWaveActionProps",
			"objdata": {
				"AdditionalPlantfood": 0,
				"Zombies": [
					{
						"Type": "RTID(beach@ZombieTypes)"
					}
				]
			}
		},
		{
			"aliases": [
				"Wave2"
			],
			"objclass": "SpawnZombiesJitteredWaveActionProps",
			"objdata": {
				"AdditionalPlantfood": 0,
				"Zombies": [
					{
						"Type": "RTID(beach@ZombieTypes)"
					}
				]
			}
		},
		{
			"aliases": [
				"Wave3"
			],
			"objclass": "SpawnZombiesJitteredWaveActionProps",
			"objdata": {
				"AdditionalPlantfood": 0,
				"Zombies": [
					{
						"Type": "RTID(beach@ZombieTypes)"
					},
					{
						"Type": "RTID(beach@ZombieTypes)"
					}
				]
			}
		},
		{
			"aliases": [
				"Wave4"
			],
			"objclass": "SpawnZombiesJitteredWaveActionProps",
			"objdata": {
				"AdditionalPlantfood": 0,
				"Zombies": [
					{
						"Type": "RTID(beach@ZombieTypes)"
					}
				]
			}
		},
		{
			"aliases": [
				"Wave5"
			],
			"objclass": "SpawnZombiesJitteredWaveActionProps",
			"objdata": {
				"AdditionalPlantfood": 0,
				"Zombies": [
					{
						"Type": "RTID(beach_armor1@ZombieTypes)"
					}
				]
			}
		},
		{
			"aliases": [
				"Wave6"
			],
			"objclass": "SpawnZombiesJitteredWaveActionProps",
			"objdata": {
				"AdditionalPlantfood": 1,
				"Zombies": [
					{
						"Type": "RTID(beach_armor2@ZombieTypes)"
					}
				]
			}
		},
		{
			"aliases": [
				"Wave7"
			],
			"objclass": "SpawnZombiesJitteredWaveActionProps",
			"objdata": {
				"AdditionalPlantfood": 0,
				"Zombies": [
					{
						"Type": "RTID(beach@ZombieTypes)"
					}
				]
			}
		},
		{
			"aliases": [
				"Wave8"
			],
			"objclass": "SpawnZombiesJitteredWaveActionProps",
			"objdata": {
				"AdditionalPlantfood": 1,
				"Zombies": [
					{
						"Type": "RTID(duckytube@ZombieTypes)"
					}
				]
			}
		},
		{
			"aliases": [
				"Wave9"
			],
			"objclass": "SpawnZombiesJitteredWaveActionProps",
			"objdata": {
				"AdditionalPlantfood": 0,
				"Zombies": [
					{
						"Type": "RTID(duckytube@ZombieTypes)"
					},
					{
						"Type": "RTID(duckytube@ZombieTypes)"
					}
				]
			}
		},
		{
			"aliases": [
				"Wave10"
			],
			"objclass": "SpawnZombiesJitteredWaveActionProps",
			"objdata": {
				"AdditionalPlantfood": 0,
				"Zombies": [
					{
						"Type": "RTID(duckytube_armor1@ZombieTypes)"
					}
				]
			}
		},
		{
			"aliases": [
				"Wave11"
			],
			"objclass": "SpawnZombiesJitteredWaveActionProps",
			"objdata": {
				"AdditionalPlantfood": 1,
				"Zombies": [
					{
						"Type": "RTID(duckytube_armor2@ZombieTypes)"
					}
				]
			}
		},
		{
			"aliases": [
				"Wave12"
			],
			"objclass": "SpawnZombiesJitteredWaveActionProps",
			"objdata": {
				"AdditionalPlantfood": 0,
				"Zombies": [
					{
						"Type": "RTID(duckytube@ZombieTypes)"
					}
				]
			}
		},
		{
			"aliases": [
				"Wave13"
			],
			"objclass": "SpawnZombiesJitteredWaveActionProps",
			"objdata": {
				"AdditionalPlantfood": 0,
				"Zombies": [
					{
						"Type": "RTID(beach_fisherman@ZombieTypes)"
					}
				]
			}
		},
		{
			"aliases": [
				"Wave14"
			],
			"objclass": "SpawnZombiesJitteredWaveActionProps",
			"objdata": {
				"AdditionalPlantfood": 1,
				"Zombies": [
					{
						"Type": "RTID(beach_fem@ZombieTypes)"
					}
				]
			}
		},
		{
			"aliases": [
				"Wave15"
			],
			"objclass": "SpawnZombiesJitteredWaveActionProps",
			"objdata": {
				"AdditionalPlantfood": 0,
				"Zombies": [
					{
						"Type": "RTID(beach_fisherman@ZombieTypes)"
					}
				]
			}
		},
		{
			"aliases": [
				"Wave16"
			],
			"objclass": "SpawnZombiesJitteredWaveActionProps",
			"objdata": {
				"AdditionalPlantfood": 0,
				"Zombies": [
					{
						"Type": "RTID(beach_fem_armor1@ZombieTypes)"
					}
				]
			}
		},
		{
			"aliases": [
				"Wave17"
			],
			"objclass": "SpawnZombiesJitteredWaveActionProps",
			"objdata": {
				"AdditionalPlantfood": 1,
				"Zombies": [
					{
						"Type": "RTID(beach_fem_armor2@ZombieTypes)"
					}
				]
			}
		},
		{
			"aliases": [
				"Wave18"
			],
			"objclass": "SpawnZombiesJitteredWaveActionProps",
			"objdata": {
				"AdditionalPlantfood": 0,
				"Zombies": [
					{
						"Type": "RTID(beach_fem@ZombieTypes)"
					}
				]
			}
		},
		{
			"aliases": [
				"Wave19"
			],
			"objclass": "SpawnZombiesJitteredWaveActionProps",
			"objdata": {
				"AdditionalPlantfood": 0,
				"Zombies": [
					{
						"Type": "RTID(beach_fisherman@ZombieTypes)"
					}
				]
			}
		},
		{
			"aliases": [
				"Wave20"
			],
			"objclass": "SpawnZombiesJitteredWaveActionProps",
			"objdata": {
				"AdditionalPlantfood": 1,
				"Zombies": [
					{
						"Type": "RTID(duckytube@ZombieTypes)"
					}
				]
			}
		},
		{
			"aliases": [
				"Wave21"
			],
			"objclass": "SpawnZombiesJitteredWaveActionProps",
			"objdata": {
				"AdditionalPlantfood": 0,
				"Zombies": [
					{
						"Type": "RTID(duckytube@ZombieTypes)"
					}
				]
			}
		},
		{
			"aliases": [
				"Gravestones"
			],
			"objclass": "GravestoneProperties",
			"objdata": {
				"ForceSpawnData": []
			}
		},
		{
			"aliases": [
				"NewWaves"
			],
			"objclass": "WaveManagerModuleProperties",
			"objdata": {}
		},
		{
			"aliases": [
				"Wave2TidalChangeEvent0"
			],
			"objclass": "TidalChangeWaveActionProps",
			"objdata": {
				"TidalChange": {
					"ChangeAmount": 5,
					"ChangeType": "absolute"
				}
			}
		},
		{
			"aliases": [
				"Wave6TidalChangeEvent0"
			],
			"objclass": "TidalChangeWaveActionProps",
			"objdata": {
				"TidalChange": {
					"ChangeAmount": 1,
					"ChangeType": "absolute"
				}
			}
		},
		{
			"aliases": [
				"Wave7TidalChangeEvent0"
			],
			"objclass": "TidalChangeWaveActionProps",
			"objdata": {
				"TidalChange": {
					"ChangeAmount": 4,
					"ChangeType": "absolute"
				}
			}
		},
		{
			"aliases": [
				"Wave7LowTideEvent0"
			],
			"objclass": "BeachStageEventZombieSpawnerProps",
			"objdata": {
				"ColumnEnd": 8,
				"ColumnStart": "4",
				"GroupSize": 1,
				"TimeBeforeFullSpawn": "0.5",
				"TimeBetweenGroups": "0.25",
				"WaveStartMessage": "[WARNING_LOW_TIDE]",
				"ZombieCount": 1,
				"ZombieName": "beach_octopus"
			}
		},
		{
			"aliases": [
				"Wave11TidalChangeEvent0"
			],
			"objclass": "TidalChangeWaveActionProps",
			"objdata": {
				"TidalChange": {
					"ChangeAmount": 7,
					"ChangeType": "absolute"
				}
			}
		},
		{
			"aliases": [
				"Wave12LowTideEvent0"
			],
			"objclass": "BeachStageEventZombieSpawnerProps",
			"objdata": {
				"ColumnEnd": 7,
				"ColumnStart": 5,
				"GroupSize": 2,
				"TimeBeforeFullSpawn": "0.5",
				"TimeBetweenGroups": "0.25",
				"WaveStartMessage": "[WARNING_LOW_TIDE]",
				"ZombieCount": 2,
				"ZombieName": "beach_imp"
			}
		},
		{
			"aliases": [
				"Wave14TidalChangeEvent0"
			],
			"objclass": "TidalChangeWaveActionProps",
			"objdata": {
				"TidalChange": {
					"ChangeAmount": 3,
					"ChangeType": "absolute"
				}
			}
		},
		{
			"aliases": [
				"Wave16TidalChangeEvent0"
			],
			"objclass": "TidalChangeWaveActionProps",
			"objdata": {
				"TidalChange": {
					"ChangeAmount": 8,
					"ChangeType": "absolute"
				}
			}
		},
		{
			"aliases": [
				"Wave18LowTideEvent0"
			],
			"objclass": "BeachStageEventZombieSpawnerProps",
			"objdata": {
				"ColumnEnd": 8,
				"ColumnStart": 3,
				"GroupSize": 1,
				"TimeBeforeFullSpawn": "0.5",
				"TimeBetweenGroups": "0.25",
				"WaveStartMessage": "[WARNING_LOW_TIDE]",
				"ZombieCount": 1,
				"ZombieName": "beach_gargantuar"
			}
		},
		{
			"aliases": [
				"Wave19TidalChangeEvent0"
			],
			"objclass": "TidalChangeWaveActionProps",
			"objdata": {
				"TidalChange": {
					"ChangeAmount": 6,
					"ChangeType": "absolute"
				}
			}
		},
		{
			"aliases": [
				"Wave20TidalChangeEvent0"
			],
			"objclass": "TidalChangeWaveActionProps",
			"objdata": {
				"TidalChange": {
					"ChangeAmount": 9,
					"ChangeType": "absolute"
				}
			}
		},
		{
			"aliases": [
				"Wave21LowTideEvent0"
			],
			"objclass": "BeachStageEventZombieSpawnerProps",
			"objdata": {
				"ColumnEnd": 8,
				"ColumnStart": 5,
				"GroupSize": 1,
				"TimeBeforeFullSpawn": "0.5",
				"TimeBetweenGroups": "0.25",
				"WaveStartMessage": "[WARNING_LOW_TIDE]",
				"ZombieCount": 1,
				"ZombieName": "beach_gargantuar"
			}
		}
	],
	"version": 1
}