{
	"#comment": "Level Of The Day Test 2",
	"objects": [
		{
			"objclass": "LevelDefinition",
			"objdata": {
				"Description": "[PLAYERS_TRIP_TO_RIFT]",
				"LevelMutator": "RTID(LevelMutator@CurrentLevel)",
				"LevelNumber": 0,
				"LevelPowerupSet": "LevelPowerupsDisabled",
				"Loot": "RTID(DefaultLoot@LevelModules)",
				"Modules": [
					"RTID(CarnivalMowers@LevelModules)",
					"RTID(DefaultZombieWinCondition@LevelModules)",
					"RTID(LevelEscalationModule@CurrentLevel)",
					"RTID(SeedBank@CurrentLevel)",
					"RTID(Gravestones@CurrentLevel)",
					"RTID(SliderPlacement@CurrentLevel)",
					"RTID(ZombiesDeadWinCon@LevelModules)",
					"RTID(StandardRiftIntro@LevelModules)",
					"RTID(PerkActivator@CurrentLevel)",
					"RTID(LevelDifficultyScaling@CurrentLevel)",
					"RTID(NewWaves@CurrentLevel)"
				],
				"Name": "[RIFT_LEVEL_NAME]",
				"PerksDisabledInLevel": [],
				"PerksDisabledPerDifficulty": [
					[],
					[],
					[]
				],
				"StageModule": "RTID(CarnivalStage@LevelModules)",
				"StartingSun": 250,
				"SuppressPlantfoodPurchase": true,
				"VictoryModule": "RTID(RiftOutro@LevelModules)"
			}
		},
		{
			"aliases": [
				"LevelEscalationModule"
			],
			"objclass": "LevelEscalationModuleProperties",
			"objdata": {
				"FlagCount": 1,
				"PlantfoodToSpawnCount": 0,
				"PointIncrementPerWave": 100,
				"StartingPoints": 50,
				"WaveManagerProps": "RTID(WaveManagerProps@CurrentLevel)",
				"WavesPerFlag": 9,
				"ZombiePool": [
					"RTID(carnie@ZombieTypes)",
					"RTID(carnie_armor1@ZombieTypes)",
					"RTID(carnie_armor2@ZombieTypes)"
				]
			}
		},
		{
			"aliases": [
				"Gravestones"
			],
			"objclass": "GravestoneProperties",
			"objdata": {
				"ForceSpawnData": [
					{
						"GridX": 4,
						"GridY": 0
					},
					{
						"GridX": 5,
						"GridY": 0
					},
					{
						"GridX": 6,
						"GridY": 0
					},
					{
						"GridX": 3,
						"GridY": 1
					},
					{
						"GridX": 4,
						"GridY": 2
					},
					{
						"GridX": 5,
						"GridY": 2
					},
					{
						"GridX": 6,
						"GridY": 2
					},
					{
						"GridX": 3,
						"GridY": 3
					},
					{
						"GridX": 4,
						"GridY": 4
					},
					{
						"GridX": 5,
						"GridY": 4
					},
					{
						"GridX": 6,
						"GridY": 4
					}
				]
			}
		},
		{
			"aliases": [
				"SliderPlacement"
			],
			"objclass": "InitialGridItemProperties",
			"objdata": {
				"InitialGridItemPlacements": [
					{
						"GridX": 6,
						"GridY": 1,
						"TypeName": "slider_up_modern"
					},
					{
						"GridX": 6,
						"GridY": 3,
						"TypeName": "slider_down_modern"
					}
				]
			}
		},
		{
			"aliases": [
				"SeedBank"
			],
			"objclass": "SeedBankProperties",
			"objdata": {
				"PlantExcludeList": [
					"spearmint",
					"peppermint",
					"appeasemint",
					"concealmint",
					"filamint",
					"wintermint",
					"bombardmint",
					"armamint",
					"ailmint",
					"reinforcemint",
					"containmint",
					"enchantmint",
					"enchantmint",
					"enforcemint",
					"enlightenmint",
					"blover"
				],
				"PresetPlantList": [],
				"SelectionMethod": "chooser"
			}
		},
		{
			"aliases": [
				"WaveManagerProps"
			],
			"objclass": "WaveManagerProperties",
			"objdata": {
				"MaxNextWaveHealthPercentage": 0.9,
				"MinNextWaveHealthPercentage": 0.8,
				"Waves": [
					[
						"RTID(Wave1@CurrentLevel)"
					],
					[
						"RTID(Wave2@CurrentLevel)"
					],
					[
						"RTID(Wave3@CurrentLevel)"
					],
					[
						"RTID(Wave4@CurrentLevel)"
					],
					[
						"RTID(Wave5@CurrentLevel)"
					],
					[
						"RTID(Wave6@CurrentLevel)"
					],
					[
						"RTID(Wave7@CurrentLevel)"
					],
					[
						"RTID(Wave8@CurrentLevel)"
					],
					[
						"RTID(Wave9@CurrentLevel)"
					]
				]
			}
		},
		{
			"aliases": [
				"Wave1"
			],
			"objclass": "SpawnZombiesJitteredWaveActionProps",
			"objdata": {
				"Zombies": [
					{
						"Row": "2",
						"Type": "RTID(carnie@ZombieTypes)"
					}
				]
			}
		},
		{
			"aliases": [
				"Wave2"
			],
			"objclass": "SpawnZombiesJitteredWaveActionProps",
			"objdata": {
				"Zombies": [
					{
						"Row": "1",
						"Type": "RTID(carnie@ZombieTypes)"
					}
				]
			}
		},
		{
			"aliases": [
				"Wave3"
			],
			"objclass": "SpawnZombiesJitteredWaveActionProps",
			"objdata": {
				"AdditionalPlantfood": 1,
				"Zombies": [
					{
						"Row": "5",
						"Type": "RTID(carnie@ZombieTypes)"
					}
				]
			}
		},
		{
			"aliases": [
				"Wave4"
			],
			"objclass": "SpawnZombiesJitteredWaveActionProps",
			"objdata": {
				"Zombies": [
					{
						"Row": "3",
						"Type": "RTID(carnie@ZombieTypes)"
					}
				]
			}
		},
		{
			"aliases": [
				"Wave5"
			],
			"objclass": "SpawnZombiesJitteredWaveActionProps",
			"objdata": {
				"Zombies": [
					{
						"Row": "4",
						"Type": "RTID(carnie@ZombieTypes)"
					}
				]
			}
		},
		{
			"aliases": [
				"Wave6"
			],
			"objclass": "SpawnZombiesJitteredWaveActionProps",
			"objdata": {
				"Zombies": [
					{
						"Row": "2",
						"Type": "RTID(carnie@ZombieTypes)"
					},
					{
						"Row": "2",
						"Type": "RTID(carnie@ZombieTypes)"
					}
				]
			}
		},
		{
			"aliases": [
				"Wave7"
			],
			"objclass": "SpawnZombiesJitteredWaveActionProps",
			"objdata": {
				"AdditionalPlantfood": 1,
				"Zombies": [
					{
						"Row": "1",
						"Type": "RTID(carnie_armor1@ZombieTypes)"
					}
				]
			}
		},
		{
			"aliases": [
				"Wave8"
			],
			"objclass": "SpawnZombiesJitteredWaveActionProps",
			"objdata": {
				"Zombies": [
					{
						"Type": "RTID(carnie@ZombieTypes)"
					},
					{
						"Row": "5",
						"Type": "RTID(carnie_armor1@ZombieTypes)"
					}
				]
			}
		},
		{
			"aliases": [
				"Wave9"
			],
			"objclass": "SpawnZombiesJitteredWaveActionProps",
			"objdata": {
				"Zombies": [
					{
						"Row": "5",
						"Type": "RTID(carnie_armor2@ZombieTypes)"
					},
					{
						"Row": "1",
						"Type": "RTID(carnie_armor2@ZombieTypes)"
					}
				]
			}
		},
		{
			"aliases": [
				"PerkActivator"
			],
			"objclass": "PerkHandlerModuleProperties",
			"objdata": {}
		},
		{
			"aliases": [
				"LevelMutator"
			],
			"objclass": "LevelMutatorModuleProperties",
			"objdata": {
				"MutatorTables": [
					"RTID(MutatorPropsRift_Circus@LevelMutatorTables)",
					"RTID(LocalChallengeMutator@CurrentLevel)",
					"RTID(LocalMainChallengeMutator@CurrentLevel)"
				]
			}
		},
		{
			"aliases": [
				"LocalMainChallengeMutator"
			],
			"objclass": "LevelMutatorTableProps",
			"objdata": {
				"Tables": [
					{
						"Level": 0,
						"ModuleType": "mainchallenge",
						"Modules": [
							"RTID(RiftBeatTheLevelChallenge@LevelModules)"
						]
					},
					{
						"Level": 1,
						"ModuleType": "mainchallenge",
						"Modules": [
							"RTID(RiftBeatTheLevelChallenge@LevelModules)"
						]
					},
					{
						"Level": 2,
						"ModuleType": "mainchallenge",
						"Modules": [
							"RTID(RiftBeatTheLevelChallenge@LevelModules)"
						]
					}
				]
			}
		},
		{
			"aliases": [
				"LocalChallengeMutator"
			],
			"objclass": "LevelMutatorTableProps",
			"objdata": {
				"Tables": [
					{
						"Level": 0,
						"ModuleType": "bonuschallenge",
						"Modules": [
							"RTID(DestroyGridItems1@CurrentLevel)"
						]
					},
					{
						"Level": 1,
						"ModuleType": "bonuschallenge",
						"Modules": [
							"RTID(DestroyGridItems1@CurrentLevel)",
							"RTID(PlantsLost1@CurrentLevel)"
						]
					},
					{
						"Level": 2,
						"ModuleType": "bonuschallenge",
						"Modules": [
							"RTID(DestroyGridItems2@CurrentLevel)",
							"RTID(PlantsLost2@CurrentLevel)"
						]
					}
				]
			}
		},
		{
			"aliases": [
				"DestroyGridItems1"
			],
			"objclass": "DestroyGridItemsChallengeProps",
			"objdata": {
				"GridItemType": "gravestone",
				"GridItemsToDestroy": 5,
				"ChallengeDescription": "[CHALLENGE_DESTROY_GRAVESTONES]"
			}
		},
		{
			"aliases": [
				"DestroyGridItems2"
			],
			"objclass": "DestroyGridItemsChallengeProps",
			"objdata": {
				"GridItemType": "gravestone",
				"GridItemsToDestroy": 11,
				"ChallengeDescription": "[CHALLENGE_DESTROY_GRAVESTONES]"
			}
		},
		{
			"aliases": [
				"PlantsLost1"
			],
			"objclass": "StarChallengePlantsLostProps",
			"objdata": {
				"MaximumPlantsLost": 7
			}
		},
		{
			"aliases": [
				"PlantsLost2"
			],
			"objclass": "StarChallengePlantsLostProps",
			"objdata": {
				"MaximumPlantsLost": 4
			}
		},
		{
			"aliases": [
				"NewWaves"
			],
			"objclass": "WaveManagerModuleProperties",
			"objdata": {}
		},
		{
			"aliases": [
				"LevelDifficultyScaling"
			],
			"objclass": "LevelDifficultyScalingModuleProperties",
			"objdata": {
				"DifficultyRulesType": "RiftDifficulty",
				"ZombieLevelSwaps": [
					{
						"Level": 1,
						"Swaps": [
							{
								"From": "RTID(carnie@ZombieTypes)",
								"To": [
									"RTID(carnie@ZombieTypes)"
								]
							},
							{
								"From": "RTID(carnie_armor1@ZombieTypes)",
								"To": [
									"RTID(carnie_armor1@ZombieTypes)"
								]
							},
							{
								"From": "RTID(carnie_armor2@ZombieTypes)",
								"To": [
									"RTID(carnie_armor2@ZombieTypes)"
								]
							}
						]
					},
					{
						"Level": 3,
						"Swaps": [
							{
								"From": "RTID(carnie@ZombieTypes)",
								"To": [
									"RTID(carnie@ZombieTypes)",
									"RTID(carnie_armor1@ZombieTypes)"
								]
							},
							{
								"From": "RTID(carnie_armor1@ZombieTypes)",
								"To": [
									"RTID(carnie_armor1@ZombieTypes)",
									"RTID(carnie_armor2@ZombieTypes)"
								]
							},
							{
								"From": "RTID(carnie_armor2@ZombieTypes)",
								"To": [
									"RTID(carnie_armor2@ZombieTypes)",
									"RTID(carnie_imp@ZombieTypes)"
								]
							}
						]
					},
					{
						"Level": 5,
						"Swaps": [
							{
								"From": "RTID(carnie@ZombieTypes)",
								"To": [
									"RTID(carnie_armor1@ZombieTypes)",
									"RTID(carnie_armor2@ZombieTypes)"
								]
							},
							{
								"From": "RTID(carnie_armor1@ZombieTypes)",
								"To": [
									"RTID(carnie_armor2@ZombieTypes)",
									"RTID(carnie_armor1@ZombieTypes)"
								]
							},
							{
								"From": "RTID(carnie_armor2@ZombieTypes)",
								"To": [
									"RTID(carnie_armor2@ZombieTypes)",
									"RTID(carnie_imp@ZombieTypes)"
								]
							}
						]
					}
				]
			}
		}
	],
	"version": 1
}